{
    "_links": {
        "self": {
            "href": "http:\/\/default\/sites\/default\/files\/2019-03\/xrl.png"
        },
        "type": {
            "href": "http:\/\/drupal.org\/rest\/type\/file\/file"
        },
        "http:\/\/drupal.org\/rest\/relation\/file\/file\/uid": [
            {
                "href": "http:\/\/default\/user\/1?_format=hal_json"
            }
        ]
    },
    "fid": [
        {
            "value": 845
        }
    ],
    "uuid": [
        {
            "value": "82697f47-72dd-4285-a8e0-653492223fac"
        }
    ],
    "langcode": [
        {
            "value": "en"
        }
    ],
    "_embedded": {
        "http:\/\/drupal.org\/rest\/relation\/file\/file\/uid": [
            {
                "_links": {
                    "self": {
                        "href": "http:\/\/default\/user\/1?_format=hal_json"
                    },
                    "type": {
                        "href": "http:\/\/drupal.org\/rest\/type\/user\/user"
                    }
                },
                "uuid": [
                    {
                        "value": "130dbb89-c27c-42f1-8d44-0cf8e5da27cd"
                    }
                ]
            }
        ]
    },
    "filename": [
        {
            "value": "xrl.png"
        }
    ],
    "uri": [
        {
            "value": "public:\/\/2019-03\/xrl.png",
            "url": "\/sites\/default\/files\/2019-03\/xrl.png"
        }
    ],
    "filemime": [
        {
            "value": "image\/png"
        }
    ],
    "filesize": [
        {
            "value": 8534
        }
    ],
    "status": [
        {
            "value": true
        }
    ],
    "created": [
        {
            "value": "2019-03-30T05:05:57+00:00",
            "format": "Y-m-d\\TH:i:sP"
        }
    ],
    "changed": [
        {
            "value": "2019-03-30T05:06:19+00:00",
            "format": "Y-m-d\\TH:i:sP"
        }
    ]
}