{
    "_links": {
        "self": {
            "href": "http:\/\/default\/sites\/default\/files\/2019-03\/spc2.jpg"
        },
        "type": {
            "href": "http:\/\/drupal.org\/rest\/type\/file\/file"
        },
        "http:\/\/drupal.org\/rest\/relation\/file\/file\/uid": [
            {
                "href": "http:\/\/default\/user\/1?_format=hal_json"
            }
        ]
    },
    "fid": [
        {
            "value": 336
        }
    ],
    "uuid": [
        {
            "value": "fedf4da1-16cb-4ec8-bbf7-3b04a8165bc4"
        }
    ],
    "langcode": [
        {
            "value": "en"
        }
    ],
    "_embedded": {
        "http:\/\/drupal.org\/rest\/relation\/file\/file\/uid": [
            {
                "_links": {
                    "self": {
                        "href": "http:\/\/default\/user\/1?_format=hal_json"
                    },
                    "type": {
                        "href": "http:\/\/drupal.org\/rest\/type\/user\/user"
                    }
                },
                "uuid": [
                    {
                        "value": "130dbb89-c27c-42f1-8d44-0cf8e5da27cd"
                    }
                ]
            }
        ]
    },
    "filename": [
        {
            "value": "spc2.jpg"
        }
    ],
    "uri": [
        {
            "value": "public:\/\/2019-03\/spc2.jpg",
            "url": "\/sites\/default\/files\/2019-03\/spc2.jpg"
        }
    ],
    "filemime": [
        {
            "value": "image\/jpeg"
        }
    ],
    "filesize": [
        {
            "value": 8479
        }
    ],
    "status": [
        {
            "value": true
        }
    ],
    "created": [
        {
            "value": "2019-03-15T07:59:12+00:00",
            "format": "Y-m-d\\TH:i:sP"
        }
    ],
    "changed": [
        {
            "value": "2019-03-15T08:00:10+00:00",
            "format": "Y-m-d\\TH:i:sP"
        }
    ]
}